django_enum_ex/__init__.py
django_enum_ex/enums.py
django_enum_ex/fields.py
django_enum_ex-0.2.0.dist-info/LICENSE
django_enum_ex-0.2.0.dist-info/WHEEL
django_enum_ex-0.2.0.dist-info/METADATA
django_enum_ex-0.2.0.dist-info/RECORD
